{
  "session_id": "charlie_james_s48",
  "session_type": "learning",
  "day_offset": 48,
  "domain": "scheduling",
  "reason_for_call": "Set up a reminder",
  "task_params": {
    "calendar": "personal",
    "title": "Church Outreach Night",
    "start_time": "2025-03-06T19:00:00-05:00",
    "end_time": "2025-03-06T21:00:00-05:00",
    "remind_at": "2025-03-06T17:45:00-05:00",
    "cadence": "once"
  },
  "expected_tools": [
    "list_events",
    "set_reminder"
  ],
  "gold_trajectory": [
    {
      "tool": "list_events",
      "arguments": {
        "calendar": "personal"
      }
    },
    {
      "tool": "set_reminder",
      "arguments": {
        "target_id": "evt_church_01",
        "remind_at": "2025-03-06T17:45:00-05:00",
        "cadence": "once"
      }
    }
  ],
  "local_env": {
    "tools": [
      "list_events",
      "check_conflicts",
      "create_event",
      "reschedule_event",
      "modify_event",
      "respond_to_event_invite",
      "cancel_event",
      "set_reminder",
      "track_event_updates",
      "find_alternative_slots"
    ],
    "references": [
      {
        "id": "evt_church_01",
        "type": "calendar_event",
        "attributes": {
          "title": "Church Outreach Night",
          "start_time": "2025-03-06T19:00:00-05:00",
          "end_time": "2025-03-06T21:00:00-05:00",
          "participants": [
            "youth@newhopechurch.org"
          ],
          "location": "New Hope Baptist Church",
          "calendar": "personal",
          "status": "confirmed"
        }
      },
      {
        "id": "evt_shop_02",
        "type": "calendar_event",
        "attributes": {
          "title": "Brake Job Finish-Up",
          "start_time": "2025-03-06T16:30:00-05:00",
          "end_time": "2025-03-06T18:00:00-05:00",
          "participants": [
            "leadtech@portlandgarage.com"
          ],
          "location": "Portland Garage",
          "calendar": "work",
          "status": "confirmed"
        }
      },
      {
        "id": "evt_bible_03",
        "type": "calendar_event",
        "attributes": {
          "title": "Men's Bible Study",
          "start_time": "2025-03-05T18:30:00-05:00",
          "end_time": "2025-03-05T20:00:00-05:00",
          "participants": [
            "deacon.ray@newhopechurch.org"
          ],
          "location": "New Hope Baptist Church",
          "calendar": "personal",
          "status": "confirmed"
        }
      },
      {
        "id": "evt_cycle_04",
        "type": "calendar_event",
        "attributes": {
          "title": "West End Cycling Club Ride",
          "start_time": "2025-03-08T09:00:00-05:00",
          "end_time": "2025-03-08T11:00:00-05:00",
          "participants": [
            "rides@westendcycling.org"
          ],
          "location": "Shawnee Park",
          "calendar": "personal",
          "status": "confirmed"
        }
      }
    ]
  }
}